gsettings_array.py
gsettings_array-1.0.1.dist-info/LICENSES/CC0-1.0.txt
gsettings_array-1.0.1.dist-info/LICENSES/GPL-2.0-only.txt
gsettings_array-1.0.1.dist-info/LICENSES/GPL-3.0-only.txt
gsettings_array-1.0.1.dist-info/METADATA
gsettings_array-1.0.1.dist-info/WHEEL
gsettings_array-1.0.1.dist-info/entry_points.txt
gsettings_array-1.0.1.dist-info/RECORD
