Metadata-Version: 2.1
Name: gsettings-array
Version: 1.0.1
Summary: Manipulate GSettings arrays.
Home-page: https://github.com/rindea/gsettings-array
Author: Jan Chren (rindeal)
Requires-Python: >=3.11,<4.0
Classifier: Development Status :: 5 - Production/Stable
Classifier: Environment :: Console
Classifier: Intended Audience :: Developers
Classifier: Intended Audience :: System Administrators
Classifier: License :: OSI Approved :: GNU General Public License v2 (GPLv2)
Classifier: License :: OSI Approved :: GNU General Public License v3 (GPLv3)
Classifier: Operating System :: POSIX :: Linux
Classifier: Programming Language :: Python :: 3
Classifier: Programming Language :: Python :: 3.11
Classifier: Programming Language :: Python :: 3.12
Classifier: Topic :: Desktop Environment :: Gnome
Classifier: Topic :: System :: Systems Administration
Classifier: Topic :: Utilities
Requires-Dist: pygobject (>=3.42.0,<4.0.0)
Project-URL: Repository, https://github.com/rindea/gsettings-array
